V2Ray/V2Ray.py
V2Ray/__init__.py
V2Ray-1.1.dist-info/LICENSE
V2Ray-1.1.dist-info/METADATA
V2Ray-1.1.dist-info/WHEEL
V2Ray-1.1.dist-info/top_level.txt
V2Ray-1.1.dist-info/RECORD
