Metadata-Version: 2.1
Name: V2Ray
Version: 1.1
Summary: A project that can create a VPN server(Vmess , Vless) using this script from X-UI panels
Author-email: Santrich <santricham@gmail.com>
Project-URL: Homepage, https://github.com/santrichm/python-V2Ray-API
Project-URL: Bug Tracker, https://github.com/santrichm/python-V2Ray-API/issues
Classifier: Programming Language :: Python :: 3
Classifier: License :: OSI Approved :: MIT License
Classifier: Operating System :: OS Independent
Requires-Python: >=3.10
License-File: LICENSE
